imscore/__init__.py
imscore/utils.py
imscore/aesthetic/__init__.py
imscore/aesthetic/model.py
imscore/cyclereward/bert.py
imscore/cyclereward/blip.py
imscore/cyclereward/model.py
imscore/cyclereward/vit.py
imscore/dummy/__init__.py
imscore/dummy/model.py
imscore/evalmuse/bert.py
imscore/evalmuse/model.py
imscore/evalmuse/vit.py
imscore/hps/__init__.py
imscore/hps/model.py
imscore/hpsv3/__init__.py
imscore/hpsv3/model.py
imscore/hpsv3/utils.py
imscore/imreward/bert.py
imscore/imreward/model.py
imscore/imreward/vit.py
imscore/mps/__init__.py
imscore/mps/cross.py
imscore/mps/model.py
imscore/pickscore/__init__.py
imscore/pickscore/model.py
imscore/preference/__init__.py
imscore/preference/model.py
imscore/vqascore/__init__.py
imscore/vqascore/model.py
imscore-0.0.11.dist-info/METADATA
imscore-0.0.11.dist-info/WHEEL
imscore-0.0.11.dist-info/top_level.txt
imscore-0.0.11.dist-info/RECORD
