Metadata-Version: 2.4
Name: imscore
Version: 0.0.11
Summary: A small example package
Author-email: RE-N-Y <s@krea.ai>
Classifier: Programming Language :: Python :: 3
Classifier: License :: OSI Approved :: MIT License
Classifier: Operating System :: OS Independent
Requires-Python: >=3.9
Requires-Dist: torch>=2.0.0
Requires-Dist: torchvision
Requires-Dist: transformers>=4.53.0
Requires-Dist: einops
Requires-Dist: open-clip-torch
Requires-Dist: tqdm
Requires-Dist: huggingface_hub
Requires-Dist: loguru
